epiw/__init__.py
epiw/dwf.py
epiw/grid.py
epiw/locationinfo.py
epiw/test.py
epiw/type.py
epiw-0.0.32.dist-info/METADATA
epiw-0.0.32.dist-info/WHEEL
epiw-0.0.32.dist-info/top_level.txt
epiw-0.0.32.dist-info/RECORD
